dbt/adapters/ydb/__init__.py
dbt/adapters/ydb/__version__.py
dbt/adapters/ydb/column.py
dbt/adapters/ydb/connections.py
dbt/adapters/ydb/impl.py
dbt/adapters/ydb/relation.py
dbt/include/ydb/__init__.py
dbt/include/ydb/dbt_project.yml
dbt/include/ydb/macros/adapters.sql
dbt/include/ydb/macros/catalog.sql
dbt/include/ydb/macros/generic_test_sql/accepted_values.sql
dbt/include/ydb/macros/generic_test_sql/relationships.sql
dbt/include/ydb/macros/get_custom_name/get_custom_schema.sql
dbt/include/ydb/macros/materializations/models/incremental/incremental.sql
dbt/include/ydb/macros/materializations/models/table.sql
dbt/include/ydb/macros/materializations/models/view.sql
dbt/include/ydb/macros/materializations/seeds/seed.sql
dbt/include/ydb/macros/materializations/snapshots/helpers.sql
dbt/include/ydb/macros/materializations/snapshots/snapshot.sql
dbt/include/ydb/macros/materializations/snapshots/snapshot_merge.sql
dbt/include/ydb/macros/materializations/snapshots/strategies.sql
dbt/include/ydb/profile_template.yml
dbt_ydb-0.0.12.dist-info/METADATA
dbt_ydb-0.0.12.dist-info/WHEEL
dbt_ydb-0.0.12.dist-info/RECORD
