Metadata-Version: 2.4
Name: dbt-ydb
Version: 0.0.12
Summary: DBT adapter for YDB
Author: Yandex LLC
Author-email: ydb@yandex-team.ru
Requires-Python: >=3.10,<4.0
Classifier: Programming Language :: Python :: 3
Classifier: Programming Language :: Python :: 3.10
Classifier: Programming Language :: Python :: 3.11
Classifier: Programming Language :: Python :: 3.12
Classifier: Programming Language :: Python :: 3.13
Classifier: Programming Language :: Python :: 3.14
Requires-Dist: dbt-adapters (>=1.14.8,<2.0.0)
Requires-Dist: dbt-common (>=1.23.0,<2.0.0)
Requires-Dist: dbt-core (>=1.8.0,<2.0.0)
Requires-Dist: ydb-dbapi (>=0.1.13,<0.2.0)
